COPYING
README.rst
setup.py
libredte/__init__.py
libredte.egg-info/PKG-INFO
libredte.egg-info/SOURCES.txt
libredte.egg-info/dependency_links.txt
libredte.egg-info/requires.txt
libredte.egg-info/top_level.txt
libredte/api_client/__init__.py
libredte/api_client/cobros.py
libredte/api_client/contribuyentes.py
libredte/api_client/dte.py
libredte/api_client/sistema.py