Metadata-Version: 2.1
Name: libredte
Version: 4.2.0
Summary: Cliente para realizar la integración con los servicios web de LibreDTE desde Python.
Home-page: https://github.com/LibreDTE/libredte-api-client-python
Author: LibreDTE
Author-email: dev@libredte.cl
License: LGPL
Keywords: sii chile facturación electrónica
Platform: UNKNOWN
Classifier: Development Status :: 5 - Production/Stable
Classifier: Intended Audience :: Developers
Classifier: Topic :: Software Development :: Build Tools
Classifier: License :: OSI Approved :: GNU Lesser General Public License v3 or later (LGPLv3+)
Classifier: Programming Language :: Python :: 3
License-File: COPYING
